[{"season":16,"week":-4,"winner":"BAL","away":"COL","home":"BAL","awayScore":10,"homeScore":29,"overtime":false,"awayDetails":{"team":"COL","first":3,"second":0,"third":0,"fourth":7,"overtime":-1,"final":10},"homeDetails":{"team":"BAL","first":3,"second":10,"third":6,"fourth":10,"overtime":-1,"final":29},"boxScore":"https://index.sim-football.com/NSFLS16/Boxscores/3849.html"},{"season":16,"week":-4,"winner":"YKW","away":"CHI","home":"YKW","awayScore":6,"homeScore":34,"overtime":false,"awayDetails":{"team":"CHI","first":3,"second":0,"third":0,"fourth":3,"overtime":-1,"final":6},"homeDetails":{"team":"YKW","first":14,"second":7,"third":10,"fourth":3,"overtime":-1,"final":34},"boxScore":"https://index.sim-football.com/NSFLS16/Boxscores/3850.html"},{"season":16,"week":-4,"winner":"OCO","away":"OCO","home":"SJS","awayScore":30,"homeScore":7,"overtime":false,"awayDetails":{"team":"OCO","first":6,"second":17,"third":7,"fourth":0,"overtime":-1,"final":30},"homeDetails":{"team":"SJS","first":0,"second":0,"third":0,"fourth":7,"overtime":-1,"final":7},"boxScore":"https://index.sim-football.com/NSFLS16/Boxscores/3851.html"},{"season":16,"week":-4,"winner":"AZ","away":"NOLA","home":"AZ","awayScore":10,"homeScore":39,"overtime":false,"awayDetails":{"team":"NOLA","first":3,"second":7,"third":0,"fourth":0,"overtime":-1,"final":10},"homeDetails":{"team":"AZ","first":7,"second":17,"third":9,"fourth":6,"overtime":-1,"final":39},"boxScore":"https://index.sim-football.com/NSFLS16/Boxscores/3852.html"},{"season":16,"week":-4,"winner":"PHI","away":"AUS","home":"PHI","awayScore":20,"homeScore":30,"overtime":false,"awayDetails":{"team":"AUS","first":10,"second":7,"third":0,"fourth":3,"overtime":-1,"final":20},"homeDetails":{"team":"PHI","first":10,"second":10,"third":0,"fourth":10,"overtime":-1,"final":30},"boxScore":"https://index.sim-football.com/NSFLS16/Boxscores/3853.html"},{"season":16,"week":-3,"winner":"BAL","away":"BAL","home":"COL","awayScore":38,"homeScore":7,"overtime":false,"awayDetails":{"team":"BAL","first":7,"second":21,"third":0,"fourth":10,"overtime":-1,"final":38},"homeDetails":{"team":"COL","first":0,"second":7,"third":0,"fourth":0,"overtime":-1,"final":7},"boxScore":"https://index.sim-football.com/NSFLS16/Boxscores/3854.html"},{"season":16,"week":-3,"winner":"YKW","away":"YKW","home":"CHI","awayScore":30,"homeScore":24,"overtime":false,"awayDetails":{"team":"YKW","first":7,"second":10,"third":7,"fourth":6,"overtime":-1,"final":30},"homeDetails":{"team":"CHI","first":7,"second":7,"third":3,"fourth":7,"overtime":-1,"final":24},"boxScore":"https://index.sim-football.com/NSFLS16/Boxscores/3855.html"},{"season":16,"week":-3,"winner":"SJS","away":"AZ","home":"SJS","awayScore":14,"homeScore":24,"overtime":false,"awayDetails":{"team":"AZ","first":7,"second":7,"third":0,"fourth":0,"overtime":-1,"final":14},"homeDetails":{"team":"SJS","first":7,"second":3,"third":7,"fourth":7,"overtime":-1,"final":24},"boxScore":"https://index.sim-football.com/NSFLS16/Boxscores/3856.html"},{"season":16,"week":-3,"winner":"OCO","away":"OCO","home":"AUS","awayScore":47,"homeScore":13,"overtime":false,"awayDetails":{"team":"OCO","first":17,"second":3,"third":17,"fourth":10,"overtime":-1,"final":47},"homeDetails":{"team":"AUS","first":0,"second":0,"third":7,"fourth":6,"overtime":-1,"final":13},"boxScore":"https://index.sim-football.com/NSFLS16/Boxscores/3857.html"},{"season":16,"week":-3,"winner":"PHI","away":"PHI","home":"NOLA","awayScore":27,"homeScore":24,"overtime":false,"awayDetails":{"team":"PHI","first":6,"second":0,"third":7,"fourth":14,"overtime":-1,"final":27},"homeDetails":{"team":"NOLA","first":3,"second":0,"third":7,"fourth":14,"overtime":-1,"final":24},"boxScore":"https://index.sim-football.com/NSFLS16/Boxscores/3858.html"},{"season":16,"week":-2,"winner":"AZ","away":"YKW","home":"AZ","awayScore":20,"homeScore":27,"overtime":false,"awayDetails":{"team":"YKW","first":7,"second":3,"third":10,"fourth":0,"overtime":-1,"final":20},"homeDetails":{"team":"AZ","first":7,"second":10,"third":3,"fourth":7,"overtime":-1,"final":27},"boxScore":"https://index.sim-football.com/NSFLS16/Boxscores/3859.html"},{"season":16,"week":-2,"winner":"COL","away":"COL","home":"AUS","awayScore":22,"homeScore":20,"overtime":false,"awayDetails":{"team":"COL","first":3,"second":10,"third":3,"fourth":6,"overtime":-1,"final":22},"homeDetails":{"team":"AUS","first":7,"second":0,"third":3,"fourth":10,"overtime":-1,"final":20},"boxScore":"https://index.sim-football.com/NSFLS16/Boxscores/3860.html"},{"season":16,"week":-2,"winner":"BAL","away":"OCO","home":"BAL","awayScore":27,"homeScore":28,"overtime":false,"awayDetails":{"team":"OCO","first":14,"second":0,"third":10,"fourth":3,"overtime":-1,"final":27},"homeDetails":{"team":"BAL","first":0,"second":7,"third":14,"fourth":7,"overtime":-1,"final":28},"boxScore":"https://index.sim-football.com/NSFLS16/Boxscores/3861.html"},{"season":16,"week":-2,"winner":"PHI","away":"PHI","home":"CHI","awayScore":34,"homeScore":31,"overtime":false,"awayDetails":{"team":"PHI","first":7,"second":7,"third":10,"fourth":10,"overtime":-1,"final":34},"homeDetails":{"team":"CHI","first":0,"second":14,"third":7,"fourth":10,"overtime":-1,"final":31},"boxScore":"https://index.sim-football.com/NSFLS16/Boxscores/3862.html"},{"season":16,"week":-2,"winner":"NOLA","away":"NOLA","home":"SJS","awayScore":26,"homeScore":24,"overtime":false,"awayDetails":{"team":"NOLA","first":10,"second":10,"third":6,"fourth":0,"overtime":-1,"final":26},"homeDetails":{"team":"SJS","first":10,"second":7,"third":0,"fourth":7,"overtime":-1,"final":24},"boxScore":"https://index.sim-football.com/NSFLS16/Boxscores/3863.html"},{"season":16,"week":-1,"winner":"YKW","away":"COL","home":"YKW","awayScore":3,"homeScore":41,"overtime":false,"awayDetails":{"team":"COL","first":0,"second":0,"third":3,"fourth":0,"overtime":-1,"final":3},"homeDetails":{"team":"YKW","first":10,"second":17,"third":7,"fourth":7,"overtime":-1,"final":41},"boxScore":"https://index.sim-football.com/NSFLS16/Boxscores/3864.html"},{"season":16,"week":-1,"winner":"AZ","away":"CHI","home":"AZ","awayScore":6,"homeScore":38,"overtime":false,"awayDetails":{"team":"CHI","first":3,"second":3,"third":0,"fourth":0,"overtime":-1,"final":6},"homeDetails":{"team":"AZ","first":7,"second":14,"third":7,"fourth":10,"overtime":-1,"final":38},"boxScore":"https://index.sim-football.com/NSFLS16/Boxscores/3865.html"},{"season":16,"week":-1,"winner":"OCO","away":"OCO","home":"PHI","awayScore":40,"homeScore":37,"overtime":false,"awayDetails":{"team":"OCO","first":13,"second":7,"third":14,"fourth":6,"overtime":-1,"final":40},"homeDetails":{"team":"PHI","first":7,"second":10,"third":3,"fourth":17,"overtime":-1,"final":37},"boxScore":"https://index.sim-football.com/NSFLS16/Boxscores/3866.html"},{"season":16,"week":-1,"winner":"NOLA","away":"SJS","home":"NOLA","awayScore":12,"homeScore":37,"overtime":false,"awayDetails":{"team":"SJS","first":0,"second":3,"third":2,"fourth":7,"overtime":-1,"final":12},"homeDetails":{"team":"NOLA","first":7,"second":17,"third":3,"fourth":10,"overtime":-1,"final":37},"boxScore":"https://index.sim-football.com/NSFLS16/Boxscores/3867.html"},{"season":16,"week":-1,"winner":"BAL","away":"AUS","home":"BAL","awayScore":0,"homeScore":69,"overtime":false,"awayDetails":{"team":"AUS","first":0,"second":0,"third":0,"fourth":0,"overtime":-1,"final":0},"homeDetails":{"team":"BAL","first":7,"second":24,"third":14,"fourth":24,"overtime":-1,"final":69},"boxScore":"https://index.sim-football.com/NSFLS16/Boxscores/3868.html"},{"season":16,"week":1,"winner":"BAL","away":"BAL","home":"YKW","awayScore":31,"homeScore":23,"overtime":false,"awayDetails":{"team":"BAL","first":14,"second":10,"third":0,"fourth":7,"overtime":-1,"final":31},"homeDetails":{"team":"YKW","first":7,"second":3,"third":3,"fourth":10,"overtime":-1,"final":23},"boxScore":"https://index.sim-football.com/NSFLS16/Boxscores/3869.html"},{"season":16,"week":1,"winner":"PHI","away":"COL","home":"PHI","awayScore":14,"homeScore":42,"overtime":false,"awayDetails":{"team":"COL","first":0,"second":7,"third":7,"fourth":0,"overtime":-1,"final":14},"homeDetails":{"team":"PHI","first":0,"second":14,"third":14,"fourth":14,"overtime":-1,"final":42},"boxScore":"https://index.sim-football.com/NSFLS16/Boxscores/3870.html"},{"season":16,"week":1,"winner":"CHI","away":"CHI","home":"AZ","awayScore":26,"homeScore":17,"overtime":false,"awayDetails":{"team":"CHI","first":17,"second":3,"third":3,"fourth":3,"overtime":-1,"final":26},"homeDetails":{"team":"AZ","first":7,"second":10,"third":0,"fourth":0,"overtime":-1,"final":17},"boxScore":"https://index.sim-football.com/NSFLS16/Boxscores/3871.html"},{"season":16,"week":1,"winner":"OCO","away":"OCO","home":"SJS","awayScore":28,"homeScore":19,"overtime":false,"awayDetails":{"team":"OCO","first":3,"second":0,"third":10,"fourth":15,"overtime":-1,"final":28},"homeDetails":{"team":"SJS","first":6,"second":10,"third":0,"fourth":3,"overtime":-1,"final":19},"boxScore":"https://index.sim-football.com/NSFLS16/Boxscores/3872.html"},{"season":16,"week":1,"winner":"NOLA","away":"NOLA","home":"AUS","awayScore":24,"homeScore":17,"overtime":false,"awayDetails":{"team":"NOLA","first":7,"second":3,"third":7,"fourth":7,"overtime":-1,"final":24},"homeDetails":{"team":"AUS","first":0,"second":3,"third":14,"fourth":0,"overtime":-1,"final":17},"boxScore":"https://index.sim-football.com/NSFLS16/Boxscores/3873.html"},{"season":16,"week":2,"winner":"BAL","away":"BAL","home":"COL","awayScore":23,"homeScore":21,"overtime":false,"awayDetails":{"team":"BAL","first":13,"second":3,"third":0,"fourth":7,"overtime":-1,"final":23},"homeDetails":{"team":"COL","first":7,"second":0,"third":7,"fourth":7,"overtime":-1,"final":21},"boxScore":"https://index.sim-football.com/NSFLS16/Boxscores/3874.html"},{"season":16,"week":2,"winner":"CHI","away":"YKW","home":"CHI","awayScore":20,"homeScore":33,"overtime":false,"awayDetails":{"team":"YKW","first":6,"second":0,"third":7,"fourth":7,"overtime":-1,"final":20},"homeDetails":{"team":"CHI","first":7,"second":9,"third":14,"fourth":3,"overtime":-1,"final":33},"boxScore":"https://index.sim-football.com/NSFLS16/Boxscores/3875.html"},{"season":16,"week":2,"winner":"OCO","away":"PHI","home":"OCO","awayScore":21,"homeScore":24,"overtime":false,"awayDetails":{"team":"PHI","first":7,"second":7,"third":0,"fourth":7,"overtime":-1,"final":21},"homeDetails":{"team":"OCO","first":7,"second":7,"third":3,"fourth":7,"overtime":-1,"final":24},"boxScore":"https://index.sim-football.com/NSFLS16/Boxscores/3876.html"},{"season":16,"week":2,"winner":"AZ","away":"AZ","home":"AUS","awayScore":13,"homeScore":3,"overtime":false,"awayDetails":{"team":"AZ","first":0,"second":3,"third":7,"fourth":3,"overtime":-1,"final":13},"homeDetails":{"team":"AUS","first":0,"second":0,"third":3,"fourth":0,"overtime":-1,"final":3},"boxScore":"https://index.sim-football.com/NSFLS16/Boxscores/3877.html"},{"season":16,"week":2,"winner":"SJS","away":"SJS","home":"NOLA","awayScore":23,"homeScore":20,"overtime":false,"awayDetails":{"team":"SJS","first":10,"second":0,"third":7,"fourth":6,"overtime":-1,"final":23},"homeDetails":{"team":"NOLA","first":3,"second":10,"third":0,"fourth":7,"overtime":-1,"final":20},"boxScore":"https://index.sim-football.com/NSFLS16/Boxscores/3878.html"},{"season":16,"week":3,"winner":"YKW","away":"YKW","home":"SJS","awayScore":34,"homeScore":13,"overtime":false,"awayDetails":{"team":"YKW","first":0,"second":10,"third":7,"fourth":17,"overtime":-1,"final":34},"homeDetails":{"team":"SJS","first":3,"second":7,"third":0,"fourth":3,"overtime":-1,"final":13},"boxScore":"https://index.sim-football.com/NSFLS16/Boxscores/3879.html"},{"season":16,"week":3,"winner":"CHI","away":"COL","home":"CHI","awayScore":17,"homeScore":30,"overtime":false,"awayDetails":{"team":"COL","first":0,"second":10,"third":0,"fourth":7,"overtime":-1,"final":17},"homeDetails":{"team":"CHI","first":3,"second":3,"third":14,"fourth":10,"overtime":-1,"final":30},"boxScore":"https://index.sim-football.com/NSFLS16/Boxscores/3880.html"},{"season":16,"week":3,"winner":"PHI","away":"PHI","home":"BAL","awayScore":34,"homeScore":27,"overtime":false,"awayDetails":{"team":"PHI","first":10,"second":17,"third":7,"fourth":0,"overtime":-1,"final":34},"homeDetails":{"team":"BAL","first":7,"second":3,"third":14,"fourth":3,"overtime":-1,"final":27},"boxScore":"https://index.sim-football.com/NSFLS16/Boxscores/3881.html"},{"season":16,"week":3,"winner":"AZ","away":"NOLA","home":"AZ","awayScore":0,"homeScore":34,"overtime":false,"awayDetails":{"team":"NOLA","first":0,"second":0,"third":0,"fourth":0,"overtime":-1,"final":0},"homeDetails":{"team":"AZ","first":7,"second":21,"third":3,"fourth":3,"overtime":-1,"final":34},"boxScore":"https://index.sim-football.com/NSFLS16/Boxscores/3882.html"},{"season":16,"week":3,"winner":"OCO","away":"AUS","home":"OCO","awayScore":10,"homeScore":52,"overtime":false,"awayDetails":{"team":"AUS","first":7,"second":0,"third":0,"fourth":3,"overtime":-1,"final":10},"homeDetails":{"team":"OCO","first":10,"second":0,"third":14,"fourth":28,"overtime":-1,"final":52},"boxScore":"https://index.sim-football.com/NSFLS16/Boxscores/3883.html"},{"season":16,"week":4,"winner":"YKW","away":"PHI","home":"YKW","awayScore":28,"homeScore":31,"overtime":true,"awayDetails":{"team":"PHI","first":7,"second":14,"third":7,"fourth":0,"overtime":0,"final":28},"homeDetails":{"team":"YKW","first":7,"second":0,"third":7,"fourth":14,"overtime":3,"final":31},"boxScore":"https://index.sim-football.com/NSFLS16/Boxscores/3884.html"},{"season":16,"week":4,"winner":"BAL","away":"CHI","home":"BAL","awayScore":17,"homeScore":30,"overtime":false,"awayDetails":{"team":"CHI","first":0,"second":0,"third":14,"fourth":3,"overtime":-1,"final":17},"homeDetails":{"team":"BAL","first":14,"second":10,"third":3,"fourth":3,"overtime":-1,"final":30},"boxScore":"https://index.sim-football.com/NSFLS16/Boxscores/3885.html"},{"season":16,"week":4,"winner":"AZ","away":"OCO","home":"AZ","awayScore":12,"homeScore":27,"overtime":false,"awayDetails":{"team":"OCO","first":3,"second":6,"third":3,"fourth":0,"overtime":-1,"final":12},"homeDetails":{"team":"AZ","first":3,"second":0,"third":10,"fourth":14,"overtime":-1,"final":27},"boxScore":"https://index.sim-football.com/NSFLS16/Boxscores/3886.html"},{"season":16,"week":4,"winner":"SJS","away":"SJS","home":"AUS","awayScore":25,"homeScore":22,"overtime":false,"awayDetails":{"team":"SJS","first":6,"second":7,"third":6,"fourth":6,"overtime":-1,"final":25},"homeDetails":{"team":"AUS","first":7,"second":7,"third":0,"fourth":8,"overtime":-1,"final":22},"boxScore":"https://index.sim-football.com/NSFLS16/Boxscores/3887.html"},{"season":16,"week":4,"winner":"NOLA","away":"NOLA","home":"COL","awayScore":24,"homeScore":16,"overtime":false,"awayDetails":{"team":"NOLA","first":0,"second":10,"third":14,"fourth":0,"overtime":-1,"final":24},"homeDetails":{"team":"COL","first":6,"second":3,"third":0,"fourth":7,"overtime":-1,"final":16},"boxScore":"https://index.sim-football.com/NSFLS16/Boxscores/3888.html"},{"season":16,"week":5,"winner":"YKW","away":"COL","home":"YKW","awayScore":9,"homeScore":39,"overtime":false,"awayDetails":{"team":"COL","first":0,"second":3,"third":3,"fourth":3,"overtime":-1,"final":9},"homeDetails":{"team":"YKW","first":9,"second":13,"third":10,"fourth":7,"overtime":-1,"final":39},"boxScore":"https://index.sim-football.com/NSFLS16/Boxscores/3889.html"},{"season":16,"week":5,"winner":"PHI","away":"CHI","home":"PHI","awayScore":19,"homeScore":48,"overtime":false,"awayDetails":{"team":"CHI","first":0,"second":0,"third":13,"fourth":6,"overtime":-1,"final":19},"homeDetails":{"team":"PHI","first":21,"second":13,"third":7,"fourth":7,"overtime":-1,"final":48},"boxScore":"https://index.sim-football.com/NSFLS16/Boxscores/3890.html"},{"season":16,"week":5,"winner":"SJS","away":"AZ","home":"SJS","awayScore":10,"homeScore":37,"overtime":false,"awayDetails":{"team":"AZ","first":3,"second":0,"third":7,"fourth":0,"overtime":-1,"final":10},"homeDetails":{"team":"SJS","first":0,"second":21,"third":6,"fourth":10,"overtime":-1,"final":37},"boxScore":"https://index.sim-football.com/NSFLS16/Boxscores/3891.html"},{"season":16,"week":5,"winner":"OCO","away":"OCO","home":"NOLA","awayScore":48,"homeScore":28,"overtime":false,"awayDetails":{"team":"OCO","first":14,"second":14,"third":13,"fourth":7,"overtime":-1,"final":48},"homeDetails":{"team":"NOLA","first":7,"second":14,"third":7,"fourth":0,"overtime":-1,"final":28},"boxScore":"https://index.sim-football.com/NSFLS16/Boxscores/3892.html"},{"season":16,"week":5,"winner":"BAL","away":"AUS","home":"BAL","awayScore":13,"homeScore":45,"overtime":false,"awayDetails":{"team":"AUS","first":3,"second":0,"third":3,"fourth":7,"overtime":-1,"final":13},"homeDetails":{"team":"BAL","first":14,"second":21,"third":7,"fourth":3,"overtime":-1,"final":45},"boxScore":"https://index.sim-football.com/NSFLS16/Boxscores/3893.html"},{"season":16,"week":6,"winner":"YKW","away":"YKW","home":"BAL","awayScore":33,"homeScore":25,"overtime":false,"awayDetails":{"team":"YKW","first":7,"second":10,"third":13,"fourth":3,"overtime":-1,"final":33},"homeDetails":{"team":"BAL","first":7,"second":7,"third":0,"fourth":11,"overtime":-1,"final":25},"boxScore":"https://index.sim-football.com/NSFLS16/Boxscores/3894.html"},{"season":16,"week":6,"winner":"AZ","away":"PHI","home":"AZ","awayScore":24,"homeScore":37,"overtime":false,"awayDetails":{"team":"PHI","first":0,"second":17,"third":0,"fourth":7,"overtime":-1,"final":24},"homeDetails":{"team":"AZ","first":7,"second":7,"third":13,"fourth":10,"overtime":-1,"final":37},"boxScore":"https://index.sim-football.com/NSFLS16/Boxscores/3895.html"},{"season":16,"week":6,"winner":"CHI","away":"CHI","home":"COL","awayScore":30,"homeScore":20,"overtime":false,"awayDetails":{"team":"CHI","first":6,"second":7,"third":0,"fourth":17,"overtime":-1,"final":30},"homeDetails":{"team":"COL","first":7,"second":6,"third":7,"fourth":0,"overtime":-1,"final":20},"boxScore":"https://index.sim-football.com/NSFLS16/Boxscores/3896.html"},{"season":16,"week":6,"winner":"OCO","away":"OCO","home":"AUS","awayScore":34,"homeScore":19,"overtime":false,"awayDetails":{"team":"OCO","first":7,"second":17,"third":3,"fourth":7,"overtime":-1,"final":34},"homeDetails":{"team":"AUS","first":3,"second":3,"third":6,"fourth":7,"overtime":-1,"final":19},"boxScore":"https://index.sim-football.com/NSFLS16/Boxscores/3897.html"},{"season":16,"week":6,"winner":"NOLA","away":"NOLA","home":"SJS","awayScore":37,"homeScore":30,"overtime":false,"awayDetails":{"team":"NOLA","first":7,"second":16,"third":7,"fourth":7,"overtime":-1,"final":37},"homeDetails":{"team":"SJS","first":6,"second":0,"third":10,"fourth":14,"overtime":-1,"final":30},"boxScore":"https://index.sim-football.com/NSFLS16/Boxscores/3898.html"},{"season":16,"week":7,"winner":"BAL","away":"COL","home":"BAL","awayScore":7,"homeScore":41,"overtime":false,"awayDetails":{"team":"COL","first":0,"second":0,"third":0,"fourth":7,"overtime":-1,"final":7},"homeDetails":{"team":"BAL","first":10,"second":17,"third":7,"fourth":7,"overtime":-1,"final":41},"boxScore":"https://index.sim-football.com/NSFLS16/Boxscores/3899.html"},{"season":16,"week":7,"winner":"CHI","away":"CHI","home":"YKW","awayScore":26,"homeScore":24,"overtime":false,"awayDetails":{"team":"CHI","first":0,"second":6,"third":14,"fourth":6,"overtime":-1,"final":26},"homeDetails":{"team":"YKW","first":0,"second":0,"third":3,"fourth":21,"overtime":-1,"final":24},"boxScore":"https://index.sim-football.com/NSFLS16/Boxscores/3900.html"},{"season":16,"week":7,"winner":"OCO","away":"AZ","home":"OCO","awayScore":0,"homeScore":25,"overtime":false,"awayDetails":{"team":"AZ","first":0,"second":0,"third":0,"fourth":0,"overtime":-1,"final":0},"homeDetails":{"team":"OCO","first":0,"second":6,"third":10,"fourth":9,"overtime":-1,"final":25},"boxScore":"https://index.sim-football.com/NSFLS16/Boxscores/3901.html"},{"season":16,"week":7,"winner":"PHI","away":"NOLA","home":"PHI","awayScore":16,"homeScore":27,"overtime":false,"awayDetails":{"team":"NOLA","first":0,"second":0,"third":10,"fourth":6,"overtime":-1,"final":16},"homeDetails":{"team":"PHI","first":14,"second":10,"third":3,"fourth":0,"overtime":-1,"final":27},"boxScore":"https://index.sim-football.com/NSFLS16/Boxscores/3902.html"},{"season":16,"week":7,"winner":"SJS","away":"AUS","home":"SJS","awayScore":0,"homeScore":55,"overtime":false,"awayDetails":{"team":"AUS","first":0,"second":0,"third":0,"fourth":0,"overtime":-1,"final":0},"homeDetails":{"team":"SJS","first":14,"second":10,"third":10,"fourth":21,"overtime":-1,"final":55},"boxScore":"https://index.sim-football.com/NSFLS16/Boxscores/3903.html"},{"season":16,"week":8,"winner":"CHI","away":"BAL","home":"CHI","awayScore":9,"homeScore":23,"overtime":false,"awayDetails":{"team":"BAL","first":0,"second":6,"third":3,"fourth":0,"overtime":-1,"final":9},"homeDetails":{"team":"CHI","first":7,"second":6,"third":0,"fourth":10,"overtime":-1,"final":23},"boxScore":"https://index.sim-football.com/NSFLS16/Boxscores/3904.html"},{"season":16,"week":8,"winner":"YKW","away":"YKW","home":"OCO","awayScore":36,"homeScore":31,"overtime":false,"awayDetails":{"team":"YKW","first":7,"second":14,"third":3,"fourth":12,"overtime":-1,"final":36},"homeDetails":{"team":"OCO","first":7,"second":10,"third":7,"fourth":7,"overtime":-1,"final":31},"boxScore":"https://index.sim-football.com/NSFLS16/Boxscores/3905.html"},{"season":16,"week":8,"winner":"PHI","away":"PHI","home":"COL","awayScore":42,"homeScore":10,"overtime":false,"awayDetails":{"team":"PHI","first":7,"second":7,"third":7,"fourth":21,"overtime":-1,"final":42},"homeDetails":{"team":"COL","first":0,"second":7,"third":3,"fourth":0,"overtime":-1,"final":10},"boxScore":"https://index.sim-football.com/NSFLS16/Boxscores/3906.html"},{"season":16,"week":8,"winner":"AZ","away":"SJS","home":"AZ","awayScore":17,"homeScore":35,"overtime":false,"awayDetails":{"team":"SJS","first":0,"second":0,"third":3,"fourth":14,"overtime":-1,"final":17},"homeDetails":{"team":"AZ","first":7,"second":14,"third":7,"fourth":7,"overtime":-1,"final":35},"boxScore":"https://index.sim-football.com/NSFLS16/Boxscores/3907.html"},{"season":16,"week":8,"winner":"NOLA","away":"AUS","home":"NOLA","awayScore":17,"homeScore":44,"overtime":false,"awayDetails":{"team":"AUS","first":0,"second":3,"third":7,"fourth":7,"overtime":-1,"final":17},"homeDetails":{"team":"NOLA","first":0,"second":14,"third":10,"fourth":20,"overtime":-1,"final":44},"boxScore":"https://index.sim-football.com/NSFLS16/Boxscores/3908.html"},{"season":16,"week":9,"winner":"PHI","away":"BAL","home":"PHI","awayScore":12,"homeScore":16,"overtime":false,"awayDetails":{"team":"BAL","first":3,"second":0,"third":9,"fourth":0,"overtime":-1,"final":12},"homeDetails":{"team":"PHI","first":3,"second":7,"third":6,"fourth":0,"overtime":-1,"final":16},"boxScore":"https://index.sim-football.com/NSFLS16/Boxscores/3909.html"},{"season":16,"week":9,"winner":"YKW","away":"YKW","home":"COL","awayScore":44,"homeScore":20,"overtime":false,"awayDetails":{"team":"YKW","first":13,"second":10,"third":21,"fourth":0,"overtime":-1,"final":44},"homeDetails":{"team":"COL","first":0,"second":7,"third":0,"fourth":13,"overtime":-1,"final":20},"boxScore":"https://index.sim-football.com/NSFLS16/Boxscores/3910.html"},{"season":16,"week":9,"winner":"CHI","away":"CHI","home":"AUS","awayScore":16,"homeScore":10,"overtime":false,"awayDetails":{"team":"CHI","first":0,"second":3,"third":7,"fourth":6,"overtime":-1,"final":16},"homeDetails":{"team":"AUS","first":0,"second":3,"third":0,"fourth":7,"overtime":-1,"final":10},"boxScore":"https://index.sim-football.com/NSFLS16/Boxscores/3911.html"},{"season":16,"week":9,"winner":"NOLA","away":"AZ","home":"NOLA","awayScore":24,"homeScore":42,"overtime":false,"awayDetails":{"team":"AZ","first":7,"second":7,"third":7,"fourth":3,"overtime":-1,"final":24},"homeDetails":{"team":"NOLA","first":0,"second":14,"third":21,"fourth":7,"overtime":-1,"final":42},"boxScore":"https://index.sim-football.com/NSFLS16/Boxscores/3912.html"},{"season":16,"week":9,"winner":"OCO","away":"SJS","home":"OCO","awayScore":29,"homeScore":35,"overtime":false,"awayDetails":{"team":"SJS","first":9,"second":10,"third":0,"fourth":10,"overtime":-1,"final":29},"homeDetails":{"team":"OCO","first":7,"second":7,"third":7,"fourth":14,"overtime":-1,"final":35},"boxScore":"https://index.sim-football.com/NSFLS16/Boxscores/3913.html"},{"season":16,"week":10,"winner":"CHI","away":"PHI","home":"CHI","awayScore":17,"homeScore":24,"overtime":false,"awayDetails":{"team":"PHI","first":3,"second":0,"third":7,"fourth":7,"overtime":-1,"final":17},"homeDetails":{"team":"CHI","first":10,"second":3,"third":0,"fourth":11,"overtime":-1,"final":24},"boxScore":"https://index.sim-football.com/NSFLS16/Boxscores/3914.html"},{"season":16,"week":10,"winner":"OCO","away":"OCO","home":"COL","awayScore":38,"homeScore":13,"overtime":false,"awayDetails":{"team":"OCO","first":0,"second":14,"third":10,"fourth":14,"overtime":-1,"final":38},"homeDetails":{"team":"COL","first":3,"second":0,"third":3,"fourth":7,"overtime":-1,"final":13},"boxScore":"https://index.sim-football.com/NSFLS16/Boxscores/3915.html"},{"season":16,"week":10,"winner":"SJS","away":"SJS","home":"BAL","awayScore":21,"homeScore":16,"overtime":false,"awayDetails":{"team":"SJS","first":7,"second":7,"third":0,"fourth":7,"overtime":-1,"final":21},"homeDetails":{"team":"BAL","first":7,"second":3,"third":6,"fourth":0,"overtime":-1,"final":16},"boxScore":"https://index.sim-football.com/NSFLS16/Boxscores/3916.html"},{"season":16,"week":10,"winner":"YKW","away":"NOLA","home":"YKW","awayScore":19,"homeScore":45,"overtime":false,"awayDetails":{"team":"NOLA","first":3,"second":0,"third":3,"fourth":13,"overtime":-1,"final":19},"homeDetails":{"team":"YKW","first":7,"second":24,"third":0,"fourth":14,"overtime":-1,"final":45},"boxScore":"https://index.sim-football.com/NSFLS16/Boxscores/3917.html"},{"season":16,"week":10,"winner":"AZ","away":"AUS","home":"AZ","awayScore":14,"homeScore":30,"overtime":false,"awayDetails":{"team":"AUS","first":0,"second":0,"third":7,"fourth":7,"overtime":-1,"final":14},"homeDetails":{"team":"AZ","first":7,"second":13,"third":3,"fourth":7,"overtime":-1,"final":30},"boxScore":"https://index.sim-football.com/NSFLS16/Boxscores/3918.html"},{"season":16,"week":11,"winner":"YKW","away":"YKW","home":"PHI","awayScore":34,"homeScore":33,"overtime":false,"awayDetails":{"team":"YKW","first":0,"second":7,"third":10,"fourth":17,"overtime":-1,"final":34},"homeDetails":{"team":"PHI","first":10,"second":10,"third":6,"fourth":7,"overtime":-1,"final":33},"boxScore":"https://index.sim-football.com/NSFLS16/Boxscores/3919.html"},{"season":16,"week":11,"winner":"COL","away":"COL","home":"AUS","awayScore":28,"homeScore":24,"overtime":false,"awayDetails":{"team":"COL","first":0,"second":14,"third":7,"fourth":7,"overtime":-1,"final":28},"homeDetails":{"team":"AUS","first":10,"second":7,"third":7,"fourth":0,"overtime":-1,"final":24},"boxScore":"https://index.sim-football.com/NSFLS16/Boxscores/3920.html"},{"season":16,"week":11,"winner":"BAL","away":"AZ","home":"BAL","awayScore":16,"homeScore":28,"overtime":false,"awayDetails":{"team":"AZ","first":3,"second":10,"third":3,"fourth":0,"overtime":-1,"final":16},"homeDetails":{"team":"BAL","first":7,"second":7,"third":7,"fourth":7,"overtime":-1,"final":28},"boxScore":"https://index.sim-football.com/NSFLS16/Boxscores/3921.html"},{"season":16,"week":11,"winner":"CHI","away":"SJS","home":"CHI","awayScore":10,"homeScore":24,"overtime":false,"awayDetails":{"team":"SJS","first":7,"second":3,"third":0,"fourth":0,"overtime":-1,"final":10},"homeDetails":{"team":"CHI","first":0,"second":7,"third":3,"fourth":14,"overtime":-1,"final":24},"boxScore":"https://index.sim-football.com/NSFLS16/Boxscores/3922.html"},{"season":16,"week":11,"winner":"OCO","away":"NOLA","home":"OCO","awayScore":9,"homeScore":57,"overtime":false,"awayDetails":{"team":"NOLA","first":3,"second":3,"third":3,"fourth":0,"overtime":-1,"final":9},"homeDetails":{"team":"OCO","first":7,"second":16,"third":24,"fourth":10,"overtime":-1,"final":57},"boxScore":"https://index.sim-football.com/NSFLS16/Boxscores/3923.html"},{"season":16,"week":12,"winner":"BAL","away":"BAL","home":"NOLA","awayScore":27,"homeScore":24,"overtime":true,"awayDetails":{"team":"BAL","first":14,"second":7,"third":3,"fourth":0,"overtime":3,"final":27},"homeDetails":{"team":"NOLA","first":3,"second":7,"third":0,"fourth":14,"overtime":0,"final":24},"boxScore":"https://index.sim-football.com/NSFLS16/Boxscores/3924.html"},{"season":16,"week":12,"winner":"AZ","away":"COL","home":"AZ","awayScore":17,"homeScore":27,"overtime":false,"awayDetails":{"team":"COL","first":0,"second":0,"third":10,"fourth":7,"overtime":-1,"final":17},"homeDetails":{"team":"AZ","first":3,"second":7,"third":3,"fourth":14,"overtime":-1,"final":27},"boxScore":"https://index.sim-football.com/NSFLS16/Boxscores/3925.html"},{"season":16,"week":12,"winner":"SJS","away":"PHI","home":"SJS","awayScore":34,"homeScore":38,"overtime":false,"awayDetails":{"team":"PHI","first":10,"second":10,"third":7,"fourth":7,"overtime":-1,"final":34},"homeDetails":{"team":"SJS","first":3,"second":14,"third":7,"fourth":14,"overtime":-1,"final":38},"boxScore":"https://index.sim-football.com/NSFLS16/Boxscores/3926.html"},{"season":16,"week":12,"winner":"CHI","away":"OCO","home":"CHI","awayScore":13,"homeScore":23,"overtime":false,"awayDetails":{"team":"OCO","first":0,"second":3,"third":3,"fourth":7,"overtime":-1,"final":13},"homeDetails":{"team":"CHI","first":7,"second":10,"third":3,"fourth":3,"overtime":-1,"final":23},"boxScore":"https://index.sim-football.com/NSFLS16/Boxscores/3927.html"},{"season":16,"week":12,"winner":"YKW","away":"AUS","home":"YKW","awayScore":17,"homeScore":27,"overtime":false,"awayDetails":{"team":"AUS","first":0,"second":10,"third":0,"fourth":7,"overtime":-1,"final":17},"homeDetails":{"team":"YKW","first":14,"second":7,"third":3,"fourth":3,"overtime":-1,"final":27},"boxScore":"https://index.sim-football.com/NSFLS16/Boxscores/3928.html"},{"season":16,"week":13,"winner":"OCO","away":"BAL","home":"OCO","awayScore":10,"homeScore":20,"overtime":false,"awayDetails":{"team":"BAL","first":7,"second":0,"third":0,"fourth":3,"overtime":-1,"final":10},"homeDetails":{"team":"OCO","first":7,"second":3,"third":10,"fourth":0,"overtime":-1,"final":20},"boxScore":"https://index.sim-football.com/NSFLS16/Boxscores/3929.html"},{"season":16,"week":13,"winner":"NOLA","away":"CHI","home":"NOLA","awayScore":16,"homeScore":22,"overtime":true,"awayDetails":{"team":"CHI","first":3,"second":10,"third":3,"fourth":0,"overtime":0,"final":16},"homeDetails":{"team":"NOLA","first":0,"second":6,"third":7,"fourth":3,"overtime":6,"final":22},"boxScore":"https://index.sim-football.com/NSFLS16/Boxscores/3930.html"},{"season":16,"week":13,"winner":"YKW","away":"AZ","home":"YKW","awayScore":27,"homeScore":28,"overtime":false,"awayDetails":{"team":"AZ","first":14,"second":10,"third":0,"fourth":3,"overtime":-1,"final":27},"homeDetails":{"team":"YKW","first":7,"second":3,"third":10,"fourth":8,"overtime":-1,"final":28},"boxScore":"https://index.sim-football.com/NSFLS16/Boxscores/3931.html"},{"season":16,"week":13,"winner":"SJS","away":"SJS","home":"COL","awayScore":20,"homeScore":16,"overtime":false,"awayDetails":{"team":"SJS","first":7,"second":3,"third":7,"fourth":3,"overtime":-1,"final":20},"homeDetails":{"team":"COL","first":3,"second":13,"third":0,"fourth":0,"overtime":-1,"final":16},"boxScore":"https://index.sim-football.com/NSFLS16/Boxscores/3932.html"},{"season":16,"week":13,"winner":"PHI","away":"AUS","home":"PHI","awayScore":20,"homeScore":31,"overtime":false,"awayDetails":{"team":"AUS","first":3,"second":0,"third":7,"fourth":10,"overtime":-1,"final":20},"homeDetails":{"team":"PHI","first":7,"second":10,"third":14,"fourth":0,"overtime":-1,"final":31},"boxScore":"https://index.sim-football.com/NSFLS16/Boxscores/3933.html"},{"season":16,"week":"WC","winner":"PHI","away":"PHI","home":"YKW","awayScore":35,"homeScore":34,"overtime":false,"awayDetails":{"team":"PHI","first":7,"second":14,"third":7,"fourth":7,"overtime":-1,"final":35},"homeDetails":{"team":"YKW","first":7,"second":17,"third":7,"fourth":3,"overtime":-1,"final":34},"boxScore":"https://index.sim-football.com/NSFLS16/Boxscores/3935.html"},{"season":16,"week":"WC","winner":"AZ","away":"SJS","home":"AZ","awayScore":21,"homeScore":41,"overtime":false,"awayDetails":{"team":"SJS","first":0,"second":7,"third":7,"fourth":7,"overtime":-1,"final":21},"homeDetails":{"team":"AZ","first":10,"second":17,"third":7,"fourth":7,"overtime":-1,"final":41},"boxScore":"https://index.sim-football.com/NSFLS16/Boxscores/3937.html"},{"season":16,"week":"CC","winner":"PHI","away":"PHI","home":"CHI","awayScore":47,"homeScore":34,"overtime":false,"awayDetails":{"team":"PHI","first":10,"second":6,"third":21,"fourth":10,"overtime":-1,"final":47},"homeDetails":{"team":"CHI","first":7,"second":13,"third":0,"fourth":14,"overtime":-1,"final":34},"boxScore":"https://index.sim-football.com/NSFLS16/Boxscores/3938.html"},{"season":16,"week":"CC","winner":"AZ","away":"AZ","home":"OCO","awayScore":31,"homeScore":3,"overtime":false,"awayDetails":{"team":"AZ","first":14,"second":3,"third":0,"fourth":14,"overtime":-1,"final":31},"homeDetails":{"team":"OCO","first":0,"second":0,"third":0,"fourth":3,"overtime":-1,"final":3},"boxScore":"https://index.sim-football.com/NSFLS16/Boxscores/3939.html"},{"season":16,"week":"F","winner":"AZ","away":"PHI","home":"AZ","awayScore":30,"homeScore":34,"overtime":false,"awayDetails":{"team":"PHI","first":7,"second":6,"third":10,"fourth":7,"overtime":-1,"final":30},"homeDetails":{"team":"AZ","first":7,"second":17,"third":3,"fourth":7,"overtime":-1,"final":34},"boxScore":"https://index.sim-football.com/NSFLS16/Boxscores/3940.html"}]