[{"season":9,"week":-4,"winner":"BAL","away":"OCO","home":"BAL","awayScore":27,"homeScore":34,"overtime":false,"awayDetails":{"team":"OCO","first":3,"second":3,"third":7,"fourth":14,"overtime":-1,"final":27},"homeDetails":{"team":"BAL","first":7,"second":7,"third":3,"fourth":17,"overtime":-1,"final":34},"boxScore":"https://index.sim-football.com/NSFLS09/Boxscores/2301.html"},{"season":9,"week":-4,"winner":"YKW","away":"SJS","home":"YKW","awayScore":13,"homeScore":26,"overtime":false,"awayDetails":{"team":"SJS","first":3,"second":7,"third":0,"fourth":3,"overtime":-1,"final":13},"homeDetails":{"team":"YKW","first":3,"second":10,"third":6,"fourth":7,"overtime":-1,"final":26},"boxScore":"https://index.sim-football.com/NSFLS09/Boxscores/2302.html"},{"season":9,"week":-4,"winner":"NOLA","away":"NOLA","home":"COL","awayScore":27,"homeScore":10,"overtime":false,"awayDetails":{"team":"NOLA","first":3,"second":7,"third":3,"fourth":14,"overtime":-1,"final":27},"homeDetails":{"team":"COL","first":0,"second":10,"third":0,"fourth":0,"overtime":-1,"final":10},"boxScore":"https://index.sim-football.com/NSFLS09/Boxscores/2303.html"},{"season":9,"week":-4,"winner":"AZ","away":"AZ","home":"PHI","awayScore":56,"homeScore":21,"overtime":false,"awayDetails":{"team":"AZ","first":10,"second":31,"third":15,"fourth":0,"overtime":-1,"final":56},"homeDetails":{"team":"PHI","first":7,"second":7,"third":0,"fourth":7,"overtime":-1,"final":21},"boxScore":"https://index.sim-football.com/NSFLS09/Boxscores/2304.html"},{"season":9,"week":-3,"winner":"NOLA","away":"NOLA","home":"AZ","awayScore":44,"homeScore":9,"overtime":false,"awayDetails":{"team":"NOLA","first":3,"second":14,"third":14,"fourth":13,"overtime":-1,"final":44},"homeDetails":{"team":"AZ","first":0,"second":0,"third":0,"fourth":9,"overtime":-1,"final":9},"boxScore":"https://index.sim-football.com/NSFLS09/Boxscores/2305.html"},{"season":9,"week":-3,"winner":"OCO","away":"YKW","home":"OCO","awayScore":18,"homeScore":33,"overtime":false,"awayDetails":{"team":"YKW","first":7,"second":0,"third":0,"fourth":11,"overtime":-1,"final":18},"homeDetails":{"team":"OCO","first":14,"second":6,"third":6,"fourth":7,"overtime":-1,"final":33},"boxScore":"https://index.sim-football.com/NSFLS09/Boxscores/2306.html"},{"season":9,"week":-3,"winner":"BAL","away":"SJS","home":"BAL","awayScore":20,"homeScore":42,"overtime":false,"awayDetails":{"team":"SJS","first":0,"second":3,"third":10,"fourth":7,"overtime":-1,"final":20},"homeDetails":{"team":"BAL","first":23,"second":9,"third":7,"fourth":3,"overtime":-1,"final":42},"boxScore":"https://index.sim-football.com/NSFLS09/Boxscores/2307.html"},{"season":9,"week":-3,"winner":"COL","away":"PHI","home":"COL","awayScore":14,"homeScore":24,"overtime":false,"awayDetails":{"team":"PHI","first":0,"second":14,"third":0,"fourth":0,"overtime":-1,"final":14},"homeDetails":{"team":"COL","first":7,"second":10,"third":0,"fourth":7,"overtime":-1,"final":24},"boxScore":"https://index.sim-football.com/NSFLS09/Boxscores/2308.html"},{"season":9,"week":-2,"winner":"BAL","away":"PHI","home":"BAL","awayScore":6,"homeScore":48,"overtime":false,"awayDetails":{"team":"PHI","first":0,"second":3,"third":0,"fourth":3,"overtime":-1,"final":6},"homeDetails":{"team":"BAL","first":28,"second":7,"third":3,"fourth":10,"overtime":-1,"final":48},"boxScore":"https://index.sim-football.com/NSFLS09/Boxscores/2309.html"},{"season":9,"week":-2,"winner":"YKW","away":"COL","home":"YKW","awayScore":17,"homeScore":33,"overtime":false,"awayDetails":{"team":"COL","first":10,"second":0,"third":0,"fourth":7,"overtime":-1,"final":17},"homeDetails":{"team":"YKW","first":0,"second":10,"third":17,"fourth":6,"overtime":-1,"final":33},"boxScore":"https://index.sim-football.com/NSFLS09/Boxscores/2310.html"},{"season":9,"week":-2,"winner":"OCO","away":"OCO","home":"AZ","awayScore":37,"homeScore":0,"overtime":false,"awayDetails":{"team":"OCO","first":17,"second":10,"third":7,"fourth":3,"overtime":-1,"final":37},"homeDetails":{"team":"AZ","first":0,"second":0,"third":0,"fourth":0,"overtime":-1,"final":0},"boxScore":"https://index.sim-football.com/NSFLS09/Boxscores/2311.html"},{"season":9,"week":-2,"winner":"NOLA","away":"SJS","home":"NOLA","awayScore":17,"homeScore":42,"overtime":false,"awayDetails":{"team":"SJS","first":0,"second":0,"third":10,"fourth":7,"overtime":-1,"final":17},"homeDetails":{"team":"NOLA","first":3,"second":9,"third":13,"fourth":17,"overtime":-1,"final":42},"boxScore":"https://index.sim-football.com/NSFLS09/Boxscores/2312.html"},{"season":9,"week":-1,"winner":"YKW","away":"PHI","home":"YKW","awayScore":0,"homeScore":45,"overtime":false,"awayDetails":{"team":"PHI","first":0,"second":0,"third":0,"fourth":0,"overtime":-1,"final":0},"homeDetails":{"team":"YKW","first":7,"second":14,"third":14,"fourth":10,"overtime":-1,"final":45},"boxScore":"https://index.sim-football.com/NSFLS09/Boxscores/2313.html"},{"season":9,"week":-1,"winner":"COL","away":"OCO","home":"COL","awayScore":26,"homeScore":32,"overtime":true,"awayDetails":{"team":"OCO","first":14,"second":6,"third":0,"fourth":6,"overtime":0,"final":26},"homeDetails":{"team":"COL","first":3,"second":6,"third":10,"fourth":7,"overtime":6,"final":32},"boxScore":"https://index.sim-football.com/NSFLS09/Boxscores/2314.html"},{"season":9,"week":-1,"winner":"SJS","away":"AZ","home":"SJS","awayScore":10,"homeScore":41,"overtime":false,"awayDetails":{"team":"AZ","first":0,"second":7,"third":0,"fourth":3,"overtime":-1,"final":10},"homeDetails":{"team":"SJS","first":10,"second":7,"third":7,"fourth":17,"overtime":-1,"final":41},"boxScore":"https://index.sim-football.com/NSFLS09/Boxscores/2315.html"},{"season":9,"week":-1,"winner":"NOLA","away":"BAL","home":"NOLA","awayScore":28,"homeScore":41,"overtime":false,"awayDetails":{"team":"BAL","first":7,"second":7,"third":0,"fourth":14,"overtime":-1,"final":28},"homeDetails":{"team":"NOLA","first":17,"second":7,"third":10,"fourth":7,"overtime":-1,"final":41},"boxScore":"https://index.sim-football.com/NSFLS09/Boxscores/2316.html"},{"season":9,"week":1,"winner":"BAL","away":"YKW","home":"BAL","awayScore":20,"homeScore":27,"overtime":false,"awayDetails":{"team":"YKW","first":3,"second":10,"third":7,"fourth":0,"overtime":-1,"final":20},"homeDetails":{"team":"BAL","first":7,"second":0,"third":3,"fourth":17,"overtime":-1,"final":27},"boxScore":"https://index.sim-football.com/NSFLS09/Boxscores/2317.html"},{"season":9,"week":1,"winner":"COL","away":"AZ","home":"COL","awayScore":16,"homeScore":23,"overtime":false,"awayDetails":{"team":"AZ","first":7,"second":3,"third":3,"fourth":3,"overtime":-1,"final":16},"homeDetails":{"team":"COL","first":0,"second":16,"third":7,"fourth":0,"overtime":-1,"final":23},"boxScore":"https://index.sim-football.com/NSFLS09/Boxscores/2318.html"},{"season":9,"week":1,"winner":"OCO","away":"SJS","home":"OCO","awayScore":14,"homeScore":41,"overtime":false,"awayDetails":{"team":"SJS","first":0,"second":7,"third":0,"fourth":7,"overtime":-1,"final":14},"homeDetails":{"team":"OCO","first":10,"second":14,"third":3,"fourth":14,"overtime":-1,"final":41},"boxScore":"https://index.sim-football.com/NSFLS09/Boxscores/2319.html"},{"season":9,"week":1,"winner":"NOLA","away":"NOLA","home":"PHI","awayScore":40,"homeScore":6,"overtime":false,"awayDetails":{"team":"NOLA","first":7,"second":6,"third":21,"fourth":6,"overtime":-1,"final":40},"homeDetails":{"team":"PHI","first":3,"second":0,"third":3,"fourth":0,"overtime":-1,"final":6},"boxScore":"https://index.sim-football.com/NSFLS09/Boxscores/2320.html"},{"season":9,"week":2,"winner":"BAL","away":"COL","home":"BAL","awayScore":6,"homeScore":41,"overtime":false,"awayDetails":{"team":"COL","first":0,"second":3,"third":0,"fourth":3,"overtime":-1,"final":6},"homeDetails":{"team":"BAL","first":10,"second":14,"third":14,"fourth":3,"overtime":-1,"final":41},"boxScore":"https://index.sim-football.com/NSFLS09/Boxscores/2321.html"},{"season":9,"week":2,"winner":"AZ","away":"AZ","home":"YKW","awayScore":12,"homeScore":6,"overtime":true,"awayDetails":{"team":"AZ","first":3,"second":0,"third":0,"fourth":3,"overtime":6,"final":12},"homeDetails":{"team":"YKW","first":0,"second":0,"third":3,"fourth":3,"overtime":0,"final":6},"boxScore":"https://index.sim-football.com/NSFLS09/Boxscores/2322.html"},{"season":9,"week":2,"winner":"PHI","away":"PHI","home":"SJS","awayScore":27,"homeScore":24,"overtime":false,"awayDetails":{"team":"PHI","first":3,"second":7,"third":14,"fourth":3,"overtime":-1,"final":27},"homeDetails":{"team":"SJS","first":7,"second":10,"third":0,"fourth":7,"overtime":-1,"final":24},"boxScore":"https://index.sim-football.com/NSFLS09/Boxscores/2323.html"},{"season":9,"week":2,"winner":"NOLA","away":"OCO","home":"NOLA","awayScore":22,"homeScore":40,"overtime":false,"awayDetails":{"team":"OCO","first":9,"second":3,"third":7,"fourth":3,"overtime":-1,"final":22},"homeDetails":{"team":"NOLA","first":14,"second":9,"third":10,"fourth":7,"overtime":-1,"final":40},"boxScore":"https://index.sim-football.com/NSFLS09/Boxscores/2324.html"},{"season":9,"week":3,"winner":"NOLA","away":"NOLA","home":"YKW","awayScore":23,"homeScore":10,"overtime":false,"awayDetails":{"team":"NOLA","first":10,"second":3,"third":7,"fourth":3,"overtime":-1,"final":23},"homeDetails":{"team":"YKW","first":0,"second":7,"third":3,"fourth":0,"overtime":-1,"final":10},"boxScore":"https://index.sim-football.com/NSFLS09/Boxscores/2325.html"},{"season":9,"week":3,"winner":"COL","away":"SJS","home":"COL","awayScore":7,"homeScore":20,"overtime":false,"awayDetails":{"team":"SJS","first":0,"second":0,"third":0,"fourth":7,"overtime":-1,"final":7},"homeDetails":{"team":"COL","first":3,"second":3,"third":14,"fourth":0,"overtime":-1,"final":20},"boxScore":"https://index.sim-football.com/NSFLS09/Boxscores/2326.html"},{"season":9,"week":3,"winner":"BAL","away":"BAL","home":"AZ","awayScore":24,"homeScore":9,"overtime":false,"awayDetails":{"team":"BAL","first":10,"second":7,"third":0,"fourth":7,"overtime":-1,"final":24},"homeDetails":{"team":"AZ","first":0,"second":3,"third":3,"fourth":3,"overtime":-1,"final":9},"boxScore":"https://index.sim-football.com/NSFLS09/Boxscores/2327.html"},{"season":9,"week":3,"winner":"OCO","away":"OCO","home":"PHI","awayScore":31,"homeScore":6,"overtime":false,"awayDetails":{"team":"OCO","first":14,"second":10,"third":0,"fourth":7,"overtime":-1,"final":31},"homeDetails":{"team":"PHI","first":0,"second":3,"third":3,"fourth":0,"overtime":-1,"final":6},"boxScore":"https://index.sim-football.com/NSFLS09/Boxscores/2328.html"},{"season":9,"week":4,"winner":"PHI","away":"PHI","home":"AZ","awayScore":27,"homeScore":17,"overtime":false,"awayDetails":{"team":"PHI","first":0,"second":17,"third":7,"fourth":3,"overtime":-1,"final":27},"homeDetails":{"team":"AZ","first":7,"second":0,"third":7,"fourth":3,"overtime":-1,"final":17},"boxScore":"https://index.sim-football.com/NSFLS09/Boxscores/2329.html"},{"season":9,"week":4,"winner":"OCO","away":"BAL","home":"OCO","awayScore":14,"homeScore":34,"overtime":false,"awayDetails":{"team":"BAL","first":0,"second":7,"third":7,"fourth":0,"overtime":-1,"final":14},"homeDetails":{"team":"OCO","first":14,"second":3,"third":3,"fourth":14,"overtime":-1,"final":34},"boxScore":"https://index.sim-football.com/NSFLS09/Boxscores/2330.html"},{"season":9,"week":4,"winner":"YKW","away":"YKW","home":"SJS","awayScore":27,"homeScore":16,"overtime":false,"awayDetails":{"team":"YKW","first":3,"second":7,"third":7,"fourth":10,"overtime":-1,"final":27},"homeDetails":{"team":"SJS","first":3,"second":3,"third":7,"fourth":3,"overtime":-1,"final":16},"boxScore":"https://index.sim-football.com/NSFLS09/Boxscores/2331.html"},{"season":9,"week":4,"winner":"NOLA","away":"COL","home":"NOLA","awayScore":3,"homeScore":45,"overtime":false,"awayDetails":{"team":"COL","first":3,"second":0,"third":0,"fourth":0,"overtime":-1,"final":3},"homeDetails":{"team":"NOLA","first":14,"second":10,"third":7,"fourth":14,"overtime":-1,"final":45},"boxScore":"https://index.sim-football.com/NSFLS09/Boxscores/2332.html"},{"season":9,"week":5,"winner":"BAL","away":"SJS","home":"BAL","awayScore":3,"homeScore":37,"overtime":false,"awayDetails":{"team":"SJS","first":0,"second":3,"third":0,"fourth":0,"overtime":-1,"final":3},"homeDetails":{"team":"BAL","first":17,"second":6,"third":0,"fourth":14,"overtime":-1,"final":37},"boxScore":"https://index.sim-football.com/NSFLS09/Boxscores/2333.html"},{"season":9,"week":5,"winner":"YKW","away":"OCO","home":"YKW","awayScore":13,"homeScore":28,"overtime":false,"awayDetails":{"team":"OCO","first":3,"second":3,"third":7,"fourth":0,"overtime":-1,"final":13},"homeDetails":{"team":"YKW","first":0,"second":14,"third":7,"fourth":7,"overtime":-1,"final":28},"boxScore":"https://index.sim-football.com/NSFLS09/Boxscores/2334.html"},{"season":9,"week":5,"winner":"COL","away":"PHI","home":"COL","awayScore":3,"homeScore":45,"overtime":false,"awayDetails":{"team":"PHI","first":0,"second":3,"third":0,"fourth":0,"overtime":-1,"final":3},"homeDetails":{"team":"COL","first":10,"second":7,"third":14,"fourth":14,"overtime":-1,"final":45},"boxScore":"https://index.sim-football.com/NSFLS09/Boxscores/2335.html"},{"season":9,"week":5,"winner":"NOLA","away":"AZ","home":"NOLA","awayScore":10,"homeScore":48,"overtime":false,"awayDetails":{"team":"AZ","first":0,"second":7,"third":0,"fourth":3,"overtime":-1,"final":10},"homeDetails":{"team":"NOLA","first":14,"second":13,"third":14,"fourth":7,"overtime":-1,"final":48},"boxScore":"https://index.sim-football.com/NSFLS09/Boxscores/2336.html"},{"season":9,"week":6,"winner":"YKW","away":"YKW","home":"COL","awayScore":35,"homeScore":28,"overtime":false,"awayDetails":{"team":"YKW","first":7,"second":7,"third":7,"fourth":14,"overtime":-1,"final":35},"homeDetails":{"team":"COL","first":0,"second":14,"third":7,"fourth":7,"overtime":-1,"final":28},"boxScore":"https://index.sim-football.com/NSFLS09/Boxscores/2337.html"},{"season":9,"week":6,"winner":"OCO","away":"AZ","home":"OCO","awayScore":16,"homeScore":65,"overtime":false,"awayDetails":{"team":"AZ","first":3,"second":6,"third":7,"fourth":0,"overtime":-1,"final":16},"homeDetails":{"team":"OCO","first":0,"second":28,"third":21,"fourth":16,"overtime":-1,"final":65},"boxScore":"https://index.sim-football.com/NSFLS09/Boxscores/2338.html"},{"season":9,"week":6,"winner":"NOLA","away":"NOLA","home":"SJS","awayScore":45,"homeScore":7,"overtime":false,"awayDetails":{"team":"NOLA","first":21,"second":7,"third":3,"fourth":14,"overtime":-1,"final":45},"homeDetails":{"team":"SJS","first":0,"second":0,"third":7,"fourth":0,"overtime":-1,"final":7},"boxScore":"https://index.sim-football.com/NSFLS09/Boxscores/2339.html"},{"season":9,"week":6,"winner":"BAL","away":"BAL","home":"PHI","awayScore":41,"homeScore":16,"overtime":false,"awayDetails":{"team":"BAL","first":6,"second":7,"third":7,"fourth":21,"overtime":-1,"final":41},"homeDetails":{"team":"PHI","first":6,"second":3,"third":7,"fourth":0,"overtime":-1,"final":16},"boxScore":"https://index.sim-football.com/NSFLS09/Boxscores/2340.html"},{"season":9,"week":7,"winner":"BAL","away":"NOLA","home":"BAL","awayScore":23,"homeScore":38,"overtime":false,"awayDetails":{"team":"NOLA","first":7,"second":6,"third":10,"fourth":0,"overtime":-1,"final":23},"homeDetails":{"team":"BAL","first":10,"second":7,"third":7,"fourth":14,"overtime":-1,"final":38},"boxScore":"https://index.sim-football.com/NSFLS09/Boxscores/2341.html"},{"season":9,"week":7,"winner":"AZ","away":"SJS","home":"AZ","awayScore":17,"homeScore":29,"overtime":false,"awayDetails":{"team":"SJS","first":3,"second":0,"third":14,"fourth":0,"overtime":-1,"final":17},"homeDetails":{"team":"AZ","first":7,"second":16,"third":3,"fourth":3,"overtime":-1,"final":29},"boxScore":"https://index.sim-football.com/NSFLS09/Boxscores/2342.html"},{"season":9,"week":7,"winner":"OCO","away":"COL","home":"OCO","awayScore":31,"homeScore":38,"overtime":false,"awayDetails":{"team":"COL","first":7,"second":10,"third":7,"fourth":7,"overtime":-1,"final":31},"homeDetails":{"team":"OCO","first":10,"second":21,"third":7,"fourth":0,"overtime":-1,"final":38},"boxScore":"https://index.sim-football.com/NSFLS09/Boxscores/2343.html"},{"season":9,"week":7,"winner":"PHI","away":"YKW","home":"PHI","awayScore":17,"homeScore":38,"overtime":false,"awayDetails":{"team":"YKW","first":0,"second":0,"third":17,"fourth":0,"overtime":-1,"final":17},"homeDetails":{"team":"PHI","first":7,"second":17,"third":7,"fourth":7,"overtime":-1,"final":38},"boxScore":"https://index.sim-football.com/NSFLS09/Boxscores/2344.html"},{"season":9,"week":8,"winner":"BAL","away":"BAL","home":"YKW","awayScore":31,"homeScore":20,"overtime":false,"awayDetails":{"team":"BAL","first":10,"second":7,"third":14,"fourth":0,"overtime":-1,"final":31},"homeDetails":{"team":"YKW","first":7,"second":3,"third":0,"fourth":10,"overtime":-1,"final":20},"boxScore":"https://index.sim-football.com/NSFLS09/Boxscores/2345.html"},{"season":9,"week":8,"winner":"COL","away":"COL","home":"AZ","awayScore":31,"homeScore":27,"overtime":false,"awayDetails":{"team":"COL","first":7,"second":10,"third":7,"fourth":7,"overtime":-1,"final":31},"homeDetails":{"team":"AZ","first":14,"second":0,"third":6,"fourth":7,"overtime":-1,"final":27},"boxScore":"https://index.sim-football.com/NSFLS09/Boxscores/2346.html"},{"season":9,"week":8,"winner":"SJS","away":"OCO","home":"SJS","awayScore":23,"homeScore":28,"overtime":false,"awayDetails":{"team":"OCO","first":3,"second":6,"third":7,"fourth":7,"overtime":-1,"final":23},"homeDetails":{"team":"SJS","first":12,"second":10,"third":3,"fourth":3,"overtime":-1,"final":28},"boxScore":"https://index.sim-football.com/NSFLS09/Boxscores/2347.html"},{"season":9,"week":8,"winner":"NOLA","away":"PHI","home":"NOLA","awayScore":10,"homeScore":58,"overtime":false,"awayDetails":{"team":"PHI","first":10,"second":0,"third":0,"fourth":0,"overtime":-1,"final":10},"homeDetails":{"team":"NOLA","first":7,"second":16,"third":21,"fourth":14,"overtime":-1,"final":58},"boxScore":"https://index.sim-football.com/NSFLS09/Boxscores/2348.html"},{"season":9,"week":9,"winner":"BAL","away":"BAL","home":"COL","awayScore":31,"homeScore":13,"overtime":false,"awayDetails":{"team":"BAL","first":7,"second":7,"third":0,"fourth":17,"overtime":-1,"final":31},"homeDetails":{"team":"COL","first":0,"second":3,"third":10,"fourth":0,"overtime":-1,"final":13},"boxScore":"https://index.sim-football.com/NSFLS09/Boxscores/2349.html"},{"season":9,"week":9,"winner":"YKW","away":"YKW","home":"AZ","awayScore":45,"homeScore":10,"overtime":false,"awayDetails":{"team":"YKW","first":3,"second":14,"third":14,"fourth":14,"overtime":-1,"final":45},"homeDetails":{"team":"AZ","first":3,"second":0,"third":0,"fourth":7,"overtime":-1,"final":10},"boxScore":"https://index.sim-football.com/NSFLS09/Boxscores/2350.html"},{"season":9,"week":9,"winner":"NOLA","away":"NOLA","home":"OCO","awayScore":24,"homeScore":15,"overtime":false,"awayDetails":{"team":"NOLA","first":7,"second":17,"third":0,"fourth":0,"overtime":-1,"final":24},"homeDetails":{"team":"OCO","first":3,"second":3,"third":3,"fourth":6,"overtime":-1,"final":15},"boxScore":"https://index.sim-football.com/NSFLS09/Boxscores/2351.html"},{"season":9,"week":9,"winner":"SJS","away":"SJS","home":"PHI","awayScore":20,"homeScore":19,"overtime":false,"awayDetails":{"team":"SJS","first":0,"second":7,"third":10,"fourth":3,"overtime":-1,"final":20},"homeDetails":{"team":"PHI","first":6,"second":10,"third":0,"fourth":3,"overtime":-1,"final":19},"boxScore":"https://index.sim-football.com/NSFLS09/Boxscores/2352.html"},{"season":9,"week":10,"winner":"BAL","away":"AZ","home":"BAL","awayScore":13,"homeScore":41,"overtime":false,"awayDetails":{"team":"AZ","first":3,"second":3,"third":7,"fourth":0,"overtime":-1,"final":13},"homeDetails":{"team":"BAL","first":3,"second":7,"third":14,"fourth":17,"overtime":-1,"final":41},"boxScore":"https://index.sim-football.com/NSFLS09/Boxscores/2353.html"},{"season":9,"week":10,"winner":"OCO","away":"PHI","home":"OCO","awayScore":9,"homeScore":44,"overtime":false,"awayDetails":{"team":"PHI","first":0,"second":3,"third":6,"fourth":0,"overtime":-1,"final":9},"homeDetails":{"team":"OCO","first":14,"second":16,"third":7,"fourth":7,"overtime":-1,"final":44},"boxScore":"https://index.sim-football.com/NSFLS09/Boxscores/2354.html"},{"season":9,"week":10,"winner":"COL","away":"COL","home":"SJS","awayScore":24,"homeScore":17,"overtime":false,"awayDetails":{"team":"COL","first":6,"second":3,"third":7,"fourth":8,"overtime":-1,"final":24},"homeDetails":{"team":"SJS","first":10,"second":7,"third":0,"fourth":0,"overtime":-1,"final":17},"boxScore":"https://index.sim-football.com/NSFLS09/Boxscores/2355.html"},{"season":9,"week":10,"winner":"YKW","away":"YKW","home":"NOLA","awayScore":30,"homeScore":24,"overtime":false,"awayDetails":{"team":"YKW","first":10,"second":3,"third":10,"fourth":7,"overtime":-1,"final":30},"homeDetails":{"team":"NOLA","first":0,"second":7,"third":10,"fourth":7,"overtime":-1,"final":24},"boxScore":"https://index.sim-football.com/NSFLS09/Boxscores/2356.html"},{"season":9,"week":11,"winner":"OCO","away":"OCO","home":"BAL","awayScore":31,"homeScore":21,"overtime":false,"awayDetails":{"team":"OCO","first":14,"second":14,"third":3,"fourth":0,"overtime":-1,"final":31},"homeDetails":{"team":"BAL","first":0,"second":7,"third":7,"fourth":7,"overtime":-1,"final":21},"boxScore":"https://index.sim-football.com/NSFLS09/Boxscores/2357.html"},{"season":9,"week":11,"winner":"YKW","away":"SJS","home":"YKW","awayScore":7,"homeScore":48,"overtime":false,"awayDetails":{"team":"SJS","first":7,"second":0,"third":0,"fourth":0,"overtime":-1,"final":7},"homeDetails":{"team":"YKW","first":21,"second":6,"third":7,"fourth":14,"overtime":-1,"final":48},"boxScore":"https://index.sim-football.com/NSFLS09/Boxscores/2358.html"},{"season":9,"week":11,"winner":"NOLA","away":"NOLA","home":"COL","awayScore":34,"homeScore":14,"overtime":false,"awayDetails":{"team":"NOLA","first":6,"second":14,"third":0,"fourth":14,"overtime":-1,"final":34},"homeDetails":{"team":"COL","first":7,"second":0,"third":0,"fourth":7,"overtime":-1,"final":14},"boxScore":"https://index.sim-football.com/NSFLS09/Boxscores/2359.html"},{"season":9,"week":11,"winner":"PHI","away":"AZ","home":"PHI","awayScore":17,"homeScore":20,"overtime":true,"awayDetails":{"team":"AZ","first":7,"second":3,"third":0,"fourth":7,"overtime":0,"final":17},"homeDetails":{"team":"PHI","first":0,"second":3,"third":3,"fourth":11,"overtime":3,"final":20},"boxScore":"https://index.sim-football.com/NSFLS09/Boxscores/2360.html"},{"season":9,"week":12,"winner":"NOLA","away":"NOLA","home":"AZ","awayScore":37,"homeScore":13,"overtime":false,"awayDetails":{"team":"NOLA","first":10,"second":10,"third":7,"fourth":10,"overtime":-1,"final":37},"homeDetails":{"team":"AZ","first":7,"second":3,"third":3,"fourth":0,"overtime":-1,"final":13},"boxScore":"https://index.sim-football.com/NSFLS09/Boxscores/2361.html"},{"season":9,"week":12,"winner":"OCO","away":"YKW","home":"OCO","awayScore":19,"homeScore":30,"overtime":false,"awayDetails":{"team":"YKW","first":7,"second":10,"third":0,"fourth":2,"overtime":-1,"final":19},"homeDetails":{"team":"OCO","first":10,"second":10,"third":3,"fourth":7,"overtime":-1,"final":30},"boxScore":"https://index.sim-football.com/NSFLS09/Boxscores/2362.html"},{"season":9,"week":12,"winner":"BAL","away":"BAL","home":"SJS","awayScore":57,"homeScore":7,"overtime":false,"awayDetails":{"team":"BAL","first":10,"second":13,"third":14,"fourth":20,"overtime":-1,"final":57},"homeDetails":{"team":"SJS","first":0,"second":0,"third":7,"fourth":0,"overtime":-1,"final":7},"boxScore":"https://index.sim-football.com/NSFLS09/Boxscores/2363.html"},{"season":9,"week":12,"winner":"COL","away":"COL","home":"PHI","awayScore":21,"homeScore":7,"overtime":false,"awayDetails":{"team":"COL","first":0,"second":14,"third":7,"fourth":0,"overtime":-1,"final":21},"homeDetails":{"team":"PHI","first":2,"second":5,"third":0,"fourth":0,"overtime":-1,"final":7},"boxScore":"https://index.sim-football.com/NSFLS09/Boxscores/2364.html"},{"season":9,"week":13,"winner":"BAL","away":"PHI","home":"BAL","awayScore":7,"homeScore":54,"overtime":false,"awayDetails":{"team":"PHI","first":0,"second":7,"third":0,"fourth":0,"overtime":-1,"final":7},"homeDetails":{"team":"BAL","first":10,"second":20,"third":10,"fourth":14,"overtime":-1,"final":54},"boxScore":"https://index.sim-football.com/NSFLS09/Boxscores/2365.html"},{"season":9,"week":13,"winner":"COL","away":"COL","home":"YKW","awayScore":34,"homeScore":23,"overtime":false,"awayDetails":{"team":"COL","first":7,"second":14,"third":7,"fourth":6,"overtime":-1,"final":34},"homeDetails":{"team":"YKW","first":7,"second":7,"third":3,"fourth":6,"overtime":-1,"final":23},"boxScore":"https://index.sim-football.com/NSFLS09/Boxscores/2366.html"},{"season":9,"week":13,"winner":"OCO","away":"OCO","home":"AZ","awayScore":35,"homeScore":3,"overtime":false,"awayDetails":{"team":"OCO","first":0,"second":14,"third":7,"fourth":14,"overtime":-1,"final":35},"homeDetails":{"team":"AZ","first":0,"second":3,"third":0,"fourth":0,"overtime":-1,"final":3},"boxScore":"https://index.sim-football.com/NSFLS09/Boxscores/2367.html"},{"season":9,"week":13,"winner":"NOLA","away":"SJS","home":"NOLA","awayScore":3,"homeScore":51,"overtime":false,"awayDetails":{"team":"SJS","first":0,"second":0,"third":3,"fourth":0,"overtime":-1,"final":3},"homeDetails":{"team":"NOLA","first":7,"second":17,"third":14,"fourth":13,"overtime":-1,"final":51},"boxScore":"https://index.sim-football.com/NSFLS09/Boxscores/2368.html"},{"season":9,"week":14,"winner":"YKW","away":"PHI","home":"YKW","awayScore":23,"homeScore":52,"overtime":false,"awayDetails":{"team":"PHI","first":20,"second":3,"third":0,"fourth":0,"overtime":-1,"final":23},"homeDetails":{"team":"YKW","first":7,"second":17,"third":7,"fourth":21,"overtime":-1,"final":52},"boxScore":"https://index.sim-football.com/NSFLS09/Boxscores/2369.html"},{"season":9,"week":14,"winner":"COL","away":"OCO","home":"COL","awayScore":23,"homeScore":40,"overtime":false,"awayDetails":{"team":"OCO","first":0,"second":6,"third":14,"fourth":3,"overtime":-1,"final":23},"homeDetails":{"team":"COL","first":3,"second":10,"third":17,"fourth":10,"overtime":-1,"final":40},"boxScore":"https://index.sim-football.com/NSFLS09/Boxscores/2370.html"},{"season":9,"week":14,"winner":"AZ","away":"AZ","home":"SJS","awayScore":27,"homeScore":14,"overtime":false,"awayDetails":{"team":"AZ","first":6,"second":0,"third":14,"fourth":7,"overtime":-1,"final":27},"homeDetails":{"team":"SJS","first":0,"second":14,"third":0,"fourth":0,"overtime":-1,"final":14},"boxScore":"https://index.sim-football.com/NSFLS09/Boxscores/2371.html"},{"season":9,"week":14,"winner":"NOLA","away":"BAL","home":"NOLA","awayScore":16,"homeScore":38,"overtime":false,"awayDetails":{"team":"BAL","first":0,"second":10,"third":3,"fourth":3,"overtime":-1,"final":16},"homeDetails":{"team":"NOLA","first":3,"second":7,"third":14,"fourth":14,"overtime":-1,"final":38},"boxScore":"https://index.sim-football.com/NSFLS09/Boxscores/2372.html"},{"season":9,"week":"CC","winner":"BAL","away":"COL","home":"BAL","awayScore":34,"homeScore":40,"overtime":false,"awayDetails":{"team":"COL","first":14,"second":7,"third":7,"fourth":6,"overtime":-1,"final":34},"homeDetails":{"team":"BAL","first":7,"second":14,"third":14,"fourth":5,"overtime":-1,"final":40},"boxScore":"https://index.sim-football.com/NSFLS09/Boxscores/2373.html"},{"season":9,"week":"CC","winner":"NOLA","away":"OCO","home":"NOLA","awayScore":21,"homeScore":39,"overtime":false,"awayDetails":{"team":"OCO","first":0,"second":7,"third":7,"fourth":7,"overtime":-1,"final":21},"homeDetails":{"team":"NOLA","first":9,"second":14,"third":13,"fourth":3,"overtime":-1,"final":39},"boxScore":"https://index.sim-football.com/NSFLS09/Boxscores/2374.html"},{"season":9,"week":"F","winner":"NOLA","away":"BAL","home":"NOLA","awayScore":24,"homeScore":37,"overtime":false,"awayDetails":{"team":"BAL","first":7,"second":7,"third":10,"fourth":0,"overtime":-1,"final":24},"homeDetails":{"team":"NOLA","first":2,"second":17,"third":0,"fourth":18,"overtime":-1,"final":37},"boxScore":"https://index.sim-football.com/NSFLS09/Boxscores/2375.html"}]